prisme/__init__.py
prisme/account.py
prisme/client.py
prisme/exceptions.py
prisme/file.py
prisme/invoice.py
prisme/request.py
prisme/util.py
gl_prisme-0.2.1.dist-info/METADATA
gl_prisme-0.2.1.dist-info/WHEEL
gl_prisme-0.2.1.dist-info/licenses/LICENSE
gl_prisme-0.2.1.dist-info/RECORD
