Metadata-Version: 2.4
Name: gl-prisme
Version: 0.2.1
Summary: Prisme SOAP interface handles for python
License: MPL-2.0
License-File: LICENSE
Keywords: prisme
Author: Magenta ApS
Author-email: info@magenta.dk
Requires-Python: >=3.11,<4.0
Classifier: License :: OSI Approved
Classifier: Programming Language :: Python :: 3
Classifier: Programming Language :: Python :: 3.11
Classifier: Programming Language :: Python :: 3.12
Classifier: Programming Language :: Python :: 3.13
Classifier: Programming Language :: Python :: 3.14
Requires-Dist: dict2xml (==1.7.7)
Requires-Dist: requests (==2.32.5)
Requires-Dist: xmltodict (==1.0.2)
Requires-Dist: zeep (==4.3.2)
Project-URL: Homepage, https://magenta.dk/
Project-URL: Repository, https://git.magenta.dk/gronlandsprojekter/prisme
